argopy/__init__.py
argopy/errors.py
argopy/fetchers.py
argopy/options.py
argopy/tutorial.py
argopy/xarray.py
argopy/data_fetchers/__init__.py
argopy/data_fetchers/argovis_data.py
argopy/data_fetchers/argovis_data_processors.py
argopy/data_fetchers/erddap_data.py
argopy/data_fetchers/erddap_data_processors.py
argopy/data_fetchers/erddap_index.py
argopy/data_fetchers/erddap_refdata.py
argopy/data_fetchers/gdac_data.py
argopy/data_fetchers/gdac_data_processors.py
argopy/data_fetchers/gdac_index.py
argopy/data_fetchers/proto.py
argopy/data_fetchers/s3_data.py
argopy/extensions/__init__.py
argopy/extensions/canyon_med.py
argopy/extensions/optical_modeling.py
argopy/extensions/params_data_mode.py
argopy/extensions/utils.py
argopy/plot/__init__.py
argopy/plot/argo_colors.py
argopy/plot/dashboards.py
argopy/plot/plot.py
argopy/plot/utils.py
argopy/related/__init__.py
argopy/related/argo_documentation.py
argopy/related/doi_snapshot.py
argopy/related/euroargo_api.py
argopy/related/ocean_ops_deployments.py
argopy/related/reference_tables.py
argopy/related/topography.py
argopy/related/utils.py
argopy/static/__init__.py
argopy/static/assets/__init__.py
argopy/static/assets/admt_documentation_catalogue.json
argopy/static/assets/api_coriolis_parameter_codes.json
argopy/static/assets/data_types.json
argopy/static/assets/gdac_servers.json
argopy/static/assets/institutions.json
argopy/static/assets/nvs_reference_tables.json
argopy/static/assets/profilers.json
argopy/static/assets/sensor_metadata_examples.json
argopy/static/assets/variables_bgc_synthetic.json
argopy/static/assets/canyon-med/moy_AT_F.txt
argopy/static/assets/canyon-med/moy_AT_G.txt
argopy/static/assets/canyon-med/moy_CT_F.txt
argopy/static/assets/canyon-med/moy_CT_G.txt
argopy/static/assets/canyon-med/moy_nit_F.txt
argopy/static/assets/canyon-med/moy_nit_G.txt
argopy/static/assets/canyon-med/moy_ph_F.txt
argopy/static/assets/canyon-med/moy_ph_G.txt
argopy/static/assets/canyon-med/moy_phos_F.txt
argopy-1.3.1.dist-info/licenses/LICENSE
argopy-1.3.1.dist-info/METADATA
argopy-1.3.1.dist-info/WHEEL
argopy-1.3.1.dist-info/entry_points.txt
argopy-1.3.1.dist-info/top_level.txt
argopy-1.3.1.dist-info/RECORD
