Metadata-Version: 2.4
Name: argopy
Version: 1.3.1
Summary: A python library for Argo data beginners and experts
Home-page: https://github.com/euroargodev/argopy
Author: argopy Developers
Author-email: gmaze@ifremer.fr
Classifier: Programming Language :: Python :: 3.11
Classifier: Programming Language :: Python :: 3.12
Classifier: Topic :: Scientific/Engineering
Classifier: Intended Audience :: Science/Research
Classifier: Operating System :: OS Independent
Classifier: Operating System :: POSIX
Classifier: Operating System :: MacOS
Classifier: Operating System :: Microsoft :: Windows
Classifier: Development Status :: 5 - Production/Stable
License-File: LICENSE
Requires-Dist: xarray>=2025.7
Requires-Dist: scipy>=1.5
Requires-Dist: numpy
Requires-Dist: erddapy>=2.2.1
Requires-Dist: netCDF4>=1.5.3
Requires-Dist: h5netcdf>=1.4.0
Requires-Dist: fsspec>=2025.5.1
Requires-Dist: toolz>=0.8.2
Requires-Dist: requests>=2.28
Requires-Dist: aiohttp>=3.7
Requires-Dist: decorator>=5.1
Requires-Dist: packaging>=20.4
Dynamic: author
Dynamic: author-email
Dynamic: classifier
Dynamic: description
Dynamic: description-content-type
Dynamic: home-page
Dynamic: license-file
Dynamic: requires-dist
Dynamic: summary
